{
	"name": "Eocarcinus",
	"read_by_default": true,
	"icon": "paleopedia:textures/items/eocarcinus_icon.png",
	"category": "lepidodendron:jurassic_animal",
	"turnin": "lepidodendron:pf_adv_book_eocarcinus",
	"pages": [
		{
			"trigger": "lepidodendron:pf_adv_book_eocarcinus",
			"title": "Eocarcinus",
			"type": "quest",
			"text": "$(l)Temporal Range:$() Jurassic$(br2)$(l)Habitat:$() $(br2)>Crustacea $(br)>Malacostraca $(br)>Decapoda $(br)>Eocarcinidae"
		},
		{
			"type": "image",
			"images": ["paleopedia:textures/eocarcinus.png"],
			"title": "E. praecursor",
			"text": ""
		},
		{
			"advancement": "lepidodendron:pf_adv_book_eocarcinus",
			"type": "text",
			"text": ""
		},
		{
			"advancement": "lepidodendron:pf_adv_book_eocarcinus",
			"type": "text",
			"text": "$(l)Eats:$() Fish Food$(br)$(l)Breeds with:$() Fish Food$(br)$(l)Egg Type:$() Drops Egg$(br)$(l)Method of Obtaining:$() Bucket"
		}
	]
}
