{
    "display": {
        "icon": {
            "item": "lepidodendron:tupandactylus_navigans_raw"
        },
        "title": {
            "translate": "advancements.pf_adv_book_tupandactylus_navigans.title"
        },
        "description": {
            "translate": "advancements.pf_adv_book_tupandactylus_navigans.description"
        }
    },
    "parent": "lepidodendron:pf_base_adv_knowledge",
    "hidden": true,
    "criteria": {
        "pf_trigger": {
            "trigger": "pf_book_tupandactylus_navigans"
        }
    }
}