{
  "group": "lepidodendron",
  "type": "minecraft:crafting_shaped",
  "pattern": [
    " 1 ",
    "345",
    "678"
  ],
  "key": {
    "1": {
      "type": "forge:ore_dict",
      "ore": "stickWood"
    },
    "3": {
      "item": "lepidodendron:archaeanthus_planks"
    },
    "4": {
      "item": "lepidodendron:archaeanthus_planks"
    },
    "5": {
      "item": "lepidodendron:archaeanthus_planks"
    },
    "6": {
      "item": "lepidodendron:archaeanthus_planks"
    },
    "7": {
      "item": "lepidodendron:archaeanthus_planks"
    },
    "8": {
      "item": "lepidodendron:archaeanthus_planks"
    }
  },
  "result": {
    "item": "lepidodendron:archaeanthus_trapdoor",
    "count": 2
  }
}


















































