{
	"name": "Hylonomus",
	"read_by_default": true,
	"icon": "paleopedia:carboniferous/carboniferous_icon/hylonomus_icon.png",
	"category": "lepidodendron:carboniferous_animal",
	"turnin": "lepidodendron:pf_adv_book_hylonomus",
	"pages": [
		{
			"trigger": "lepidodendron:pf_adv_book_hylonomus",
			"title": "Hylonomus",
			"type": "quest",
			"text": "$(l)Temporal Range:$() Carbonifeorus$(br2)$(l)Habitat:$() Terrestrial$(br2)>Reptilia$(br)>Romeriida"
		},
		{
			"type": "image",
			"images": ["paleopedia:carboniferous/hylonomus.png"],
			"title": "Hylonomus lyelli",
			"text": ""
		},
		{
			"advancement": "lepidodendron:pf_adv_book_hylonomus",
			"type": "text",
			"text": "Hylonomus was a small reptilian animal from the Late Carboniferous period. Its fossils have been found in moss stumps supposing that these animals may have taken shelter in the logs, gotten trapped, and died as a result."
		},
		{
			"advancement": "lepidodendron:pf_adv_book_hylonomus",
			"type": "text",
			"text": "$(l)Eats:$() Raw Meat$(br)$(l)Breeds with:$() Raw Meat$(br)$(l)Egg Type:$() Moss Egg$(br)$(l)Method of Obtaining:$() Egg Collection Phial"
		}
	]
}

