{
	"name": "Megalocephalus",
	"read_by_default": true,
	"icon": "paleopedia:textures/megalocephalus_icon.png",
	"category": "lepidodendron:carboniferous_animal",
	"turnin": "lepidodendron:pf_adv_book_megalocephalus",
	"pages": [
		{
			"trigger": "lepidodendron:pf_adv_book_megalocephalus",
			"title": "Megalocephalus",
			"type": "quest",
			"text": "$(l)Temporal Range:$() Carboniferous$(br2)$(l)Habitat:$() Swamps$(br2)>Tetrapoda$(br)>Baphetidae$(br)>Loxommatinae"
		},
		{
			"type": "image",
			"images": ["paleopedia:textures/megalocephalus.png"],
			"title": "Megalocephalus sp.",
			"text": ""
		},
		{
			"advancement": "lepidodendron:pf_adv_book_megalocephalus",
			"type": "text",
			"text": "Megalocephalus was a Late Carboniferous carnivorous amphibian which measured up to 1.5 meters. It is known from its skull and it had long pointed teeth, with a really hard bite force."
		},
		{
			"advancement": "lepidodendron:pf_adv_book_megalocephalus",
			"type": "text",
			"text": "$(l)Eats:$() Fish$(br)$(l)Breeds with:$() Fish$(br)$(l)Egg Type:$() Spawn like Egg$(br)$(l)Method of Obtaining:$() Egg Collection Phial"
		}
	]
}

