{
	"name": "Coral Reef",
	"read_by_default": true,
	"icon": "paleopedia:textures/category_icon/icon_devonian.png",
	"category": "lepidodendron:devonian/devonian_biome",
	"pages": [
		{
			"type": "lepidodendron:headerlesstext",
			"text": "$(l)Devonian Coral Reef$(br2)$()All mobile creatures that can be found here in the mod, in alphabetical order."
		},
		{
			"type": "lepidodendron:biomespawns1",
			"biome": "lepidodendron:devonian_reef2",
			"imageid0": "lepidodendron:devonian_reef2",
			"imageid1": "lepidodendron:devonian_reef2",
			"imageid2": "lepidodendron:devonian_reef2",
			"imageid3": "lepidodendron:devonian_reef2",
			"imageid4": "lepidodendron:devonian_reef2",
			"imageid5": "lepidodendron:devonian_reef2",
			"imageid6": "lepidodendron:devonian_reef2",
			"imageid7": "lepidodendron:devonian_reef2",
			"imageid8": "lepidodendron:devonian_reef2",
			"imageid9": "lepidodendron:devonian_reef2",
			"imageid10": "lepidodendron:devonian_reef2",
			"imageid11": "lepidodendron:devonian_reef2",
			"imageid12": "lepidodendron:devonian_reef2",
			"imageid13": "lepidodendron:devonian_reef2"
		},
		{
			"type": "lepidodendron:biomespawns2",
			"biome": "lepidodendron:devonian_reef2",
			"imageid0": "lepidodendron:devonian_reef2",
			"imageid1": "lepidodendron:devonian_reef2",
			"imageid2": "lepidodendron:devonian_reef2",
			"imageid3": "lepidodendron:devonian_reef2",
			"imageid4": "lepidodendron:devonian_reef2",
			"imageid5": "lepidodendron:devonian_reef2",
			"imageid6": "lepidodendron:devonian_reef2",
			"imageid7": "lepidodendron:devonian_reef2",
			"imageid8": "lepidodendron:devonian_reef2",
			"imageid9": "lepidodendron:devonian_reef2",
			"imageid10": "lepidodendron:devonian_reef2",
			"imageid11": "lepidodendron:devonian_reef2",
			"imageid12": "lepidodendron:devonian_reef2",
			"imageid13": "lepidodendron:devonian_reef2",
			"imageid14": "lepidodendron:devonian_reef2"
		},
		{
			"type": "lepidodendron:biomespawns3",
			"biome": "lepidodendron:devonian_reef2",
			"imageid0": "lepidodendron:devonian_reef2",
			"imageid1": "lepidodendron:devonian_reef2",
			"imageid2": "lepidodendron:devonian_reef2",
			"imageid3": "lepidodendron:devonian_reef2",
			"imageid4": "lepidodendron:devonian_reef2",
			"imageid5": "lepidodendron:devonian_reef2",
			"imageid6": "lepidodendron:devonian_reef2",
			"imageid7": "lepidodendron:devonian_reef2",
			"imageid8": "lepidodendron:devonian_reef2",
			"imageid9": "lepidodendron:devonian_reef2",
			"imageid10": "lepidodendron:devonian_reef2",
			"imageid11": "lepidodendron:devonian_reef2",
			"imageid12": "lepidodendron:devonian_reef2",
			"imageid13": "lepidodendron:devonian_reef2",
			"imageid14": "lepidodendron:devonian_reef2"
		},
		{
			"type": "lepidodendron:biomespawns4",
			"biome": "lepidodendron:devonian_reef2",
			"imageid0": "lepidodendron:devonian_reef2",
			"imageid1": "lepidodendron:devonian_reef2",
			"imageid2": "lepidodendron:devonian_reef2",
			"imageid3": "lepidodendron:devonian_reef2",
			"imageid4": "lepidodendron:devonian_reef2",
			"imageid5": "lepidodendron:devonian_reef2",
			"imageid6": "lepidodendron:devonian_reef2",
			"imageid7": "lepidodendron:devonian_reef2",
			"imageid8": "lepidodendron:devonian_reef2",
			"imageid9": "lepidodendron:devonian_reef2",
			"imageid10": "lepidodendron:devonian_reef2",
			"imageid11": "lepidodendron:devonian_reef2",
			"imageid12": "lepidodendron:devonian_reef2",
			"imageid13": "lepidodendron:devonian_reef2",
			"imageid14": "lepidodendron:devonian_reef2"
		},
		{
			"type": "lepidodendron:biomespawns5",
			"biome": "lepidodendron:devonian_reef2",
			"imageid0": "lepidodendron:devonian_reef2",
			"imageid1": "lepidodendron:devonian_reef2",
			"imageid2": "lepidodendron:devonian_reef2",
			"imageid3": "lepidodendron:devonian_reef2",
			"imageid4": "lepidodendron:devonian_reef2",
			"imageid5": "lepidodendron:devonian_reef2",
			"imageid6": "lepidodendron:devonian_reef2",
			"imageid7": "lepidodendron:devonian_reef2",
			"imageid8": "lepidodendron:devonian_reef2",
			"imageid9": "lepidodendron:devonian_reef2",
			"imageid10": "lepidodendron:devonian_reef2",
			"imageid11": "lepidodendron:devonian_reef2",
			"imageid12": "lepidodendron:devonian_reef2",
			"imageid13": "lepidodendron:devonian_reef2",
			"imageid14": "lepidodendron:devonian_reef2"
		}
	]
}
