{
	"name": "Austrolimulus",
	"read_by_default": true,
	"icon": "paleopedia:textures/austrolimulus_icon.png",
	"category": "lepidodendron:triassic_animal",
	"turnin": "lepidodendron:pf_adv_book_austrolimulus",
	"pages": [
		{
			"trigger": "lepidodendron:pf_adv_book_austrolimulus",
			"title": "Austrolimulus",
			"type": "quest",
			"text": "$(l)Temporal Range:$() Triassic$(br2)$(l)Habitat:$() Deltas$(br2)>Chelicerata$(br)>Xiphosura$(br)>Austrolimulidae"
		},
		{
			"type": "image",
			"images": ["paleopedia:textures/austrolimulus.png"],
			"title": "A. fletcheri",
			"text": ""
		},
		{
			"advancement": "lepidodendron:pf_adv_book_austrolimulus",
			"type": "text",
			"text": ""
		},
		{
			"advancement": "lepidodendron:pf_adv_book_austrolimulus",
			"type": "text",
			"text": "$(l)Eats:$() Fish Food$(br)$(l)Breeds with:$() Fish Food$(br)$(l)Egg Type:$() Drops Egg$(br)$(l)Method of Obtaining:$() Bucket"
		}
	]
}

