{
	"name": "Orthrozanclus",
	"read_by_default": true,
	"icon": "paleopedia:textures/items/orthrozanclus_icon.png",
	"category": "lepidodendron:cambrian_animal",
	"turnin": "lepidodendron:pf_adv_book_orthrozanclus",
	"pages": [
		{
			"trigger": "lepidodendron:pf_adv_book_orthrozanclus",
			"title": "Orthrozanclus",
			"type": "quest",
			"text": "$(l)Temporal Range:$() Cambrian$(br2)>Mollusca$(br2)>Halkieriidae"
		},
		{
			"type": "image",
			"images": ["paleopedia:textures/orthrozanclus.png"],
			"title": "O. reburrus",
			"text": ""
		},
		{
			"advancement": "lepidodendron:pf_adv_book_orthrozanclus",
			"type": "text",
			"text": "O. reburrus is a species of Orthrozanclus with wild spines along its body. Compared to the Chengjiang version, O. elongata, whose spines were more orderly and similar length, O. reburrus' spines had long spines and a slim body that tapered towards the rear and was convex on the top."
		},
		{
			"type": "lepidodendron:diet",
			"mob": "lepidodendron:prehistoric_flora_orthrozanclus"
		},
		{
			"type": "lepidodendron:biomelocations1",
			"mob": "lepidodendron:prehistoric_flora_orthrozanclus"
		},
		{
			"type": "lepidodendron:biomelocations2",
			"mob": "lepidodendron:prehistoric_flora_orthrozanclus"
		},
		{
			"type": "lepidodendron:biomelocations3",
			"mob": "lepidodendron:prehistoric_flora_orthrozanclus"
		},
		{
			"type": "lepidodendron:biomelocations4",
			"mob": "lepidodendron:prehistoric_flora_orthrozanclus"
		}
	]
}
