{
	"name": "Precambrian Jellyfish",
	"read_by_default": true,
	"icon": "paleopedia:textures/precambrianjelly_icon.png",
	"category": "lepidodendron:precambrian_animal",
	"turnin": "lepidodendron:pf_adv_book_jellyfish_precambrian",
	"pages": [
		{
			"trigger": "lepidodendron:pf_adv_book_jellyfish_precambrian",
			"title": "Precambrian Jellyfish",
			"type": "quest",
			"text": "$(l)Temporal Range:$() Ediacaran$(br2)$(l)Habitat:$() Marine$(br2)>Cnidaria"
		},
		{
			"type": "image",
			"images": ["paleopedia:textures/precambrian_jelly.png"],
			"title": "Precambrian Jellyfish",
			"text": ""
		},
		{
			"advancement": "lepidodendron:pf_adv_book_jellyfish_precambrian",
			"type": "text",
			"text": "Jellyfish are one of the oldest animals on earth, next to sponges, and evidence has shown that some types of jellyfish existed in the Ediacaran period. They likely looked similar to modern day jellyfish."
		},
		{
			"advancement": "lepidodendron:pf_adv_book_jellyfish_precambrian",
			"type": "text",
			"text": "$(l)Eats:$() N/A$(br)$(l)Breeds with:$() Fish Food$(br)$(l)Egg Type:$() Planula$(br)$(l)Method of Obtaining:$() Bucket"
		}
	]
}
