{
	"name": "Vaveliksia",
	"read_by_default": true,
	"icon": "lepidodendron:tribrachidium",
	"category": "lepidodendron:statics",
	"turnin": "lepidodendron:pf_adv_book_vaveliksia",
	"pages": [
		{
			"trigger": "lepidodendron:pf_adv_book_vaveliksia",
			"title": "Vaveliksia",
			"type": "quest",
			"text": "$(l)Temporal Range:$() Neoproterozoic (Ediacaran)$(br2)$(l)Habitat:$() Marine$(br2)>Porifera(?)"
		},
		{
			"type": "multiblock",
			"name": "V. velikanovi",
			"enable_visualize": false,
			"multiblock": {
				"pattern": [
					[ "1" ],
					[ "0" ]
				],
				"mapping": {
					"1": "lepidodendron:tribrachidium",
					"0": "minecraft:air"
				}
			}
		},
		{
			"advancement": "lepidodendron:pf_adv_book_vaveliksia",
			"type": "text",
			"text": "Vaveliksia comes from the Upper Ediacaran, with fossils found in the Dniester River, Ukraine and White Sea, Russia. It is tubular sponge-like lifeform found in shallow waters and could grow up to 10 cm in height, and possibly partook in filter feeding from the surrounding water."
		},
		{
			"advancement": "lepidodendron:pf_adv_book_vaveliksia",
			"type": "text",
			"text": "The generic name derives from the name of Vyacheslav A. Velikanov, a Ukrainian Geologist."
		},
		{
			"advancement": "lepidodendron:pf_adv_book_vaveliksia",
			"type": "text",
			"text": "$(l)Eats:$() N/A$(br)$(l)Breeds with:$() N/A$(br)$(l)Egg Type:$() N/A$(br)$(l)Method of Obtaining:$() Shears"
		}
	]
}