{
	"name": "Parnaibaia",
	"read_by_default": true,
	"icon": "paleopedia:textures/items/parnaibaia_icon.png",
	"category": "lepidodendron:mobs",
	"turnin": "lepidodendron:pf_adv_book_parnaibaia",
	"pages": [
		{
			"trigger": "lepidodendron:pf_adv_book_parnaibaia",
			"title": "Parnaibaia",
			"type": "quest",
			"text": "$(l)Temporal Range:$() Jurassic$(br2)>Chordata$(br)>Sarcopterygii$(br)>Actinistia$(br)>Coelacanthiformes$(br)>Mawsoniidae"
		},
		{
			"type": "image",
			"images": ["paleopedia:textures/parnaibaia.png"],
			"title": "P. maranhaoensis",
			"text": ""
		},
		{
			"advancement": "lepidodendron:pf_adv_book_parnaibaia",
			"type": "text",
			"text": "Parnaibaia was a genus of mawsoniid coelacanth fish that lived during the Late Jurassic (around 161.2 - 145.5 million years ago). Its remains have been found in what is now Brazil, specifically at the Pastos Bons Formation, a locale consisting of sandstones and shales formed by ancient rivers or lakes, indicating that this was a freshwater fish. A modestly sized coelacanth, Parnaibaia measured around half a metre (just under 2 feet) long."
		},
		{
			"type": "lepidodendron:diet",
			"mob": "lepidodendron:prehistoric_flora_parnaibaia"
		},
		{
			"type": "lepidodendron:biomelocations1",
			"mob": "lepidodendron:prehistoric_flora_parnaibaia"
		},
		{
			"type": "lepidodendron:biomelocations2",
			"mob": "lepidodendron:prehistoric_flora_parnaibaia"
		},
		{
			"type": "lepidodendron:biomelocations3",
			"mob": "lepidodendron:prehistoric_flora_parnaibaia"
		},
		{
			"type": "lepidodendron:biomelocations4",
			"mob": "lepidodendron:prehistoric_flora_parnaibaia"
		}
	]
}
