{
	"name": "Rayonnoceras",
	"read_by_default": true,
	"icon": "lepidodendron:shell_rayonnoceras",
	"category": "lepidodendron:mobs",
	"turnin": "lepidodendron:pf_adv_book_rayonnoceras",
	"pages": [
		{
			"trigger": "lepidodendron:pf_adv_book_rayonnoceras",
			"title": "Rayonnoceras",
			"type": "quest",
			"text": "$(l)Temporal Range:$() Carboniferous$(br2)>Cephalopoda$(br)>Pseudorthocerida$(br)>Carbactinoceratidae"
		},
		{
			"type": "image",
			"images": ["paleopedia:textures/rayonnoceras.png"],
			"title": "R. solidiforme",
			"text": ""
		},
		{
			"advancement": "lepidodendron:pf_adv_book_rayonnoceras",
			"type": "text",
			"text": "Rayonnoceras is a Carboniferous orthocone cephalopod. Its large straight shell had many rings on it and it had a canal system within its siphuncle. Its orientation during life would have been horizontal, like some other orthocones that preceded it."
		},
		{
			"type": "lepidodendron:diet",
			"mob": "lepidodendron:prehistoric_flora_rayonnoceras"
		},
		{
			"type": "lepidodendron:biomelocations1",
			"mob": "lepidodendron:prehistoric_flora_rayonnoceras"
		},
		{
			"type": "lepidodendron:biomelocations2",
			"mob": "lepidodendron:prehistoric_flora_rayonnoceras"
		},
		{
			"type": "lepidodendron:biomelocations3",
			"mob": "lepidodendron:prehistoric_flora_rayonnoceras"
		},
		{
			"type": "lepidodendron:biomelocations4",
			"mob": "lepidodendron:prehistoric_flora_rayonnoceras"
		}
	]
}
